mlads_lukem_fyp/MLADS.py
mlads_lukem_fyp/__init__.py
mlads_lukem_fyp/databaser.py
mlads_lukem_fyp/detector.py
mlads_lukem_fyp/feature_extraction.py
mlads_lukem_fyp/ui.py
scripts/MLADS.py
scripts/__init__.py
scripts/databaser.py
scripts/detector.py
scripts/feature_extraction.py
scripts/ui.py
mlads_lukem_fyp-1.0.5.dist-info/LICENSE
mlads_lukem_fyp-1.0.5.dist-info/METADATA
mlads_lukem_fyp-1.0.5.dist-info/WHEEL
mlads_lukem_fyp-1.0.5.dist-info/top_level.txt
mlads_lukem_fyp-1.0.5.dist-info/RECORD
