Metadata-Version: 2.1
Name: mlads-lukem-fyp
Version: 1.0.5
Summary: Machine Learning Anomaly Detection System
Home-page: https://github.com/rizzapum/FYP
Author: Luke Morris
Author-email: lamorris@bradford.ac.uk
License: MIT
Platform: UNKNOWN
Classifier: License :: OSI Approved :: MIT License
Classifier: Programming Language :: Python
Classifier: Programming Language :: Python :: 3
Classifier: Programming Language :: Python :: 3.6
Requires-Python: >=3.6.0
Requires-Dist: sklearn
Requires-Dist: numpy
Requires-Dist: scapy
